resemblyzer/__init__.py
resemblyzer/audio.py
resemblyzer/hparams.py
resemblyzer/pretrained.pt
resemblyzer/voice_encoder.py
Resemblyzer_python3.9-3.0.1.dist-info/LICENSE
Resemblyzer_python3.9-3.0.1.dist-info/METADATA
Resemblyzer_python3.9-3.0.1.dist-info/WHEEL
Resemblyzer_python3.9-3.0.1.dist-info/top_level.txt
Resemblyzer_python3.9-3.0.1.dist-info/RECORD
