Metadata-Version: 2.1
Name: Resemblyzer-python3.9
Version: 3.0.1
Summary: Analyze and compare voices with deep learning
Home-page: https://github.com/zixian-zang-ai/Resemblyzer-python3.9
License: UNKNOWN
Platform: UNKNOWN
Classifier: Programming Language :: Python :: 3
Classifier: License :: OSI Approved :: Apache Software License
Classifier: Operating System :: OS Independent
Requires-Python: >=3.5
Requires-Dist: librosa (>=0.9.1)
Requires-Dist: matplotlib (>=3.0.0)
Requires-Dist: numpy (>=1.20.0)
Requires-Dist: scipy (>=1.2.1)
Requires-Dist: sounddevice
Requires-Dist: torch (==1.7.1)
Requires-Dist: tqdm
Requires-Dist: umap-learn
Requires-Dist: webrtcvad-wheels (>=2.0.14)
